aws_es_query.py
aws_es_query-0.2.0.dist-info/LICENSE
aws_es_query-0.2.0.dist-info/METADATA
aws_es_query-0.2.0.dist-info/WHEEL
aws_es_query-0.2.0.dist-info/entry_points.txt
aws_es_query-0.2.0.dist-info/top_level.txt
aws_es_query-0.2.0.dist-info/RECORD
